{
  "Round": 5,
  "ActiveSBoxes": [
    false,
    true,
    true,
    false
  ],
  "IsFirst": false,
  "IsLast": true,
  "IsBeforeLast": false,
  "Probability": 0.0077505111694335938,
  "InputDifference": 514,
  "ExpectedDifference": 544,
  "Characteristics": [
    {
      "$type": "DCAPathFinder.Logic.Cipher3.Cipher3Characteristic, DCAPathFinder",
      "InputDifferentials": [
        514,
        5,
        256,
        64,
        544
      ],
      "OutputDifferentials": [
        257,
        4,
        512,
        96
      ],
      "Probability": 0.0032958984375
    },
    {
      "$type": "DCAPathFinder.Logic.Cipher3.Cipher3Characteristic, DCAPathFinder",
      "InputDifferentials": [
        514,
        80,
        512,
        64,
        544
      ],
      "OutputDifferentials": [
        514,
        64,
        512,
        96
      ],
      "Probability": 0.0032958984375
    },
    {
      "$type": "DCAPathFinder.Logic.Cipher3.Cipher3Characteristic, DCAPathFinder",
      "InputDifferentials": [
        514,
        5,
        273,
        112,
        544
      ],
      "OutputDifferentials": [
        257,
        7,
        546,
        96
      ],
      "Probability": 0.0004634857177734375
    },
    {
      "$type": "DCAPathFinder.Logic.Cipher3.Cipher3Characteristic, DCAPathFinder",
      "InputDifferentials": [
        514,
        80,
        546,
        112,
        544
      ],
      "OutputDifferentials": [
        514,
        112,
        546,
        96
      ],
      "Probability": 0.0004634857177734375
    },
    {
      "$type": "DCAPathFinder.Logic.Cipher3.Cipher3Characteristic, DCAPathFinder",
      "InputDifferentials": [
        514,
        5,
        4113,
        176,
        544
      ],
      "OutputDifferentials": [
        257,
        11,
        8226,
        96
      ],
      "Probability": 0.00011587142944335938
    },
    {
      "$type": "DCAPathFinder.Logic.Cipher3.Cipher3Characteristic, DCAPathFinder",
      "InputDifferentials": [
        514,
        80,
        8226,
        176,
        544
      ],
      "OutputDifferentials": [
        514,
        176,
        8226,
        96
      ],
      "Probability": 0.00011587142944335938
    }
  ],
  "UnfilteredPairList": [],
  "FilteredPairList": [],
  "EncrypedPairList": [],
  "SearchPolicy": 2,
  "AbortingPolicy": 1,
  "SelectedAlgorithm": 2
}