<?xml version="1.0" encoding="utf-8"?>
<sample>
  <!--- - - - - - - - - - - - - - - - - - - - - - - - - - - - - - - - - - - - - - - - - - - - - - - - - -->
  <!--File name: NextSmallerPrime.xml-->
  <!--Last edited: 2021.04.30-->
  <!--- - - - - - - - - - - - - - - - - - - - - - - - - - - - - - - - - - - - - - - - - - - - - - - - - -->
  <!--- - - - - - - - - - - - - - - - - - - - - - - - - - - - - - - - - - - - - - - - - - - - - - - - - -->
  <!--Language 'en' starts here:-->
  <!--- - - - - - - - - - - - - - - - - - - - - - - - - - - - - - - - - - - - - - - - - - - - - - - - - -->
  <title lang="en">Next Smaller Prime Number</title>
  <summary lang="en">Find the next smaller prime number</summary>
  <description lang="en">This template searches for the biggest prime number that is smaller or equal to a given number using a loop.</description>
  <keywords>prime, composite, primality</keywords>
  <replacements lang="en">
    <replacement key="$Number Input$" value="Number Input" />
    <replacement key="$PrimeTest$" value="PrimeTest" />
    <replacement key="$Is Prime?$" value="Is Prime?" />
    <replacement key="$Next smaller prime$" value="Next Smaller Prime" />
    <replacement key="$Step Size$" value="Step Size" />
    <replacement key="$Difference$" value="Difference" />
    <replacement key="$Subtraction$" value="Subtraction" />
    <replacement key="$memo$" value="The number given in the &quot;Number Input&quot; component is decreased in a loop until a prime number is found. You can change the step size to 1 to search for the next bigger prime number." />
  </replacements>
  <!--- - - - - - - - - - - - - - - - - - - - - - - - - - - - - - - - - - - - - - - - - - - - - - - - - -->
  <!--Language 'zh' starts here:-->
  <!--- - - - - - - - - - - - - - - - - - - - - - - - - - - - - - - - - - - - - - - - - - - - - - - - - -->
  <title lang="zh">下一个较小的素数</title>
  <summary lang="zh">查找下一个较小的素数</summary>
  <description lang="zh">该模板使用循环搜索小于或等于给定数字的最大质数。</description>
  <keywords lang="zh">素数，复合，素数</keywords>
  <replacements lang="zh">
    <replacement key="$Number Input$" value="输入数字" />
    <replacement key="$PrimeTest$" value="首要测试" />
    <replacement key="$Is Prime?$" value="是素数？" />
    <replacement key="$Next smaller prime$" value="下一个较小的素数" />
    <replacement key="$Step Size$" value="增量" />
    <replacement key="$Difference$" value="区别" />
    <replacement key="$Subtraction$" value="减法" />
    <replacement key="$memo$" value="在“数字输入”组件中给定的数字将循环向下计数，直到找到质数。您可以将步长更改为1以查找下一个最大的质数。" />
  </replacements>
  <!--- - - - - - - - - - - - - - - - - - - - - - - - - - - - - - - - - - - - - - - - - - - - - - - - - -->
  <!--Language 'ru' starts here:-->
  <!--- - - - - - - - - - - - - - - - - - - - - - - - - - - - - - - - - - - - - - - - - - - - - - - - - -->
  <title lang="ru">Следующий меньший первичный номер</title>
  <summary lang="ru">Найдите следующее меньшее простое число</summary>
  <description lang="ru">Этот шаблон ищет наибольшее простое число, которое меньше или равно заданному числу с использованием цикла.</description>
  <keywords lang="ru">простой, составной, примитивный</keywords>
  <replacements lang="ru">
    <replacement key="$Number Input$" value="ввод номера" />
    <replacement key="$PrimeTest$" value="простоты чисел" />
    <replacement key="$Is Prime?$" value="Это здорово?" />
    <replacement key="$Next smaller prime$" value="Следующий меньший простой" />
    <replacement key="$Step Size$" value="приращение" />
    <replacement key="$Difference$" value="разница" />
    <replacement key="$Subtraction$" value="вычитание" />
    <replacement key="$memo$" value="Число, указанное в компоненте «ввод номера», подсчитывается в цикле до тех пор, пока не будет найдено простое число. Вы можете изменить размер шага на 1, чтобы найти следующее наибольшее простое число." />
  </replacements>
  <!--- - - - - - - - - - - - - - - - - - - - - - - - - - - - - - - - - - - - - - - - - - - - - - - - - -->
  <!--Language 'de' starts here:-->
  <!--- - - - - - - - - - - - - - - - - - - - - - - - - - - - - - - - - - - - - - - - - - - - - - - - - -->
  <title lang="de">Nächstkleinere Primzahl</title>
  <summary lang="de">Findet die nächstkleinere Primzahl</summary>
  <description lang="de">Diese Vorlage sucht in einer Schleife die größte Primzahl, die kleiner oder gleich einer gegebenen Zahl ist.</description>
  <keywords lang="de">Primzahl, zusammengesetzt</keywords>
  <replacements lang="de">
    <replacement key="$Number Input$" value="Zahleneingabe" />
    <replacement key="$PrimeTest$" value="Primzahltest" />
    <replacement key="$Is Prime?$" value="Ist prim?" />
    <replacement key="$Next smaller prime$" value="Nächstkleinere Primzahl" />
    <replacement key="$Step Size$" value="Schrittweite" />
    <replacement key="$Difference$" value="Differenz" />
    <replacement key="$Subtraction$" value="Subtraktion" />
    <replacement key="$memo$" value="Die in der Komponente &quot;Zahleneingabe&quot; gegebene Zahl wird in einer Schleife solange heruntergezählt, bis eine Primzahl gefunden wurde. Sie können die Schrittweite auf 1 abändern, um die nächstgrößere Primzahl zu suchen." />
  </replacements>
  <!--- - - - - - - - - - - - - - - - - - - - - - - - - - - - - - - - - - - - - - - - - - - - - - - - - -->
  <!--The general section starts here:-->
  <!--- - - - - - - - - - - - - - - - - - - - - - - - - - - - - - - - - - - - - - - - - - - - - - - - - -->
  <icon file="Factorization.png" />
  <relevantPlugins>
    <plugin name="BooleanOutput" />
    <plugin name="PrimeTest" />
    <plugin name="Gate" />
  </relevantPlugins>
</sample>