<?xml version="1.0" encoding="utf-8"?>
<!-- You can edit this file manually or with the Util/CrypDocumentationEditor -->
<documentation>
  <language culture="en" />
  <language culture="de-DE" />
  <introduction lang="en">   
The BB84 Photonbase Generator is part of the BB84 protocol implemented in CrypTool 2. It simulates the device that creates a sequence of photon bases which
are used for encoding and decoding of photons. These bases are represented by chars put together as one string. The symbol '+' describes a base of one horizontal
and one vertical photon filter and 'x' a base of two diagonal filters.
  </introduction>
  <introduction lang="de-DE">  
Der BB84-Photonenbasis-Generator ist Teil des in CrypTool 2 implementierten BB84-Protokolls. Er stellt das Gerät dar, welches eine Reihe von Photonenbasen erzeugt, 
mit deren Hilfe Photonen codiert oder decodiert werden können. Diese Basen werden durch Chars beschrieben, die zusammen als ein String ausgegeben werden. 
Das Zeichen '+' ist hierbei eine Photonenbasis aus einem horizontalen und einem vertikalen Filter, 'x' eine Basis aus zwei diagonalen Filtern.  
  </introduction>
  <usage lang="en">
  To create a base string the plugin first needs to know how many bases are needed. This amount of bases can either be changed in the setting of the plugin, or the input 
  connector named "Input length" must be used. In the second case a text input can be used -- the plugin will then count all characters, and set this as the amount of
  bases -- or number input to set the amount directly. When running the plugin a string of the defined length filled with random 'x' and 'x' characters will be
  created and sent to the "Base output" connector.
  For correct usage of the BB84 protocol this plugin can be used along with the BB84 Photon Encoder, the BB84 Photon Decoder, and the BB84-Man-In-The-Middle. 
  </usage>
  <usage lang="de-DE">
  Um den Basis-String ausgeben zu können, muss das Plugin zunächst die Anzahl der zu generiernden Basen wissen. Hierzu steht wahlweise ein Setting bereit, 
  in welchem die Anzahl eingestellt werden kann, oder es muss der Eingabekonnektor mit der Bezeichnung "Längeneingabe" benutzt werden. In letzterem Fall wird,
  wenn ein Textfeld an den Konnektor angebunden wird, die Anzahl der enthaltenen Zeichen als Stringlänge festgelegt. Wird hingegen eine Zahleneingabe gewählt, 
  wird die eingegebene Zahl direkt als Länge verwendet. Wird das Plugin ausgeführt, wird ein String mit der festgelegten Größe zufällig mit 'x'- und '+'-Zeichen gefüllt und 
  über den Konnektor "Basenausgabe" ausgegeben.
  Innerhalb des BB84-Protokolls kann dieses Plugin im Zusammenhang mit dem BB84-Photonencodierer, dem BB84-Photonendecodierer und dem BB84-Mittelsmann verwendet werden.
  </usage>
  <presentation lang="en">
  No presentation is implemented for this plugin.
  </presentation>
  <presentation lang="de-DE">
  Für dieses Plugin ist keine Präsentation implementiert.
  </presentation>
  <references>
    <linkReference>
      <link lang="en" url="http://en.wikipedia.org/wiki/BB84" />
      <caption lang="en">BB84 (Wikipedia)</caption>
      <link lang="de-DE" url="http://de.wikipedia.org/wiki/Quantenschlüsselaustausch#BB84-Protokoll" />
      <caption lang="de-DE">BB84 (Wikipedia)</caption>
    </linkReference>
    <linkReference>
      <link lang="en" url="http://en.wikipedia.org/wiki/Quantum_key_distribution" />
      <caption lang="en">Quantum key distribution (Wikipedia)</caption>
      <link lang="de-DE" url="http://de.wikipedia.org/wiki/Quantenschlüsselaustausch" />
      <caption lang="de-DE">Quantenschlüsselaustausch (Wikipedia)</caption>
    </linkReference>
  </references>
</documentation>